{
   "photos": [
      {
         "id": "AVzByhROPbs",
         "description": "Sea of Green",
         "urls": {
            "raw": "https://images.unsplash.com/photo-1522030865324-4062412a2023?ixlib=rb-1.2.1&ixid=eyJhcHBfaWQiOjYyMDE0fQ",
            "full": "https://images.unsplash.com/photo-1522030865324-4062412a2023?ixlib=rb-1.2.1&q=85&fm=jpg&crop=entropy&cs=srgb&ixid=eyJhcHBfaWQiOjYyMDE0fQ",
            "regular": "https://images.unsplash.com/photo-1522030865324-4062412a2023?ixlib=rb-1.2.1&q=80&fm=jpg&crop=entropy&cs=tinysrgb&w=1080&fit=max&ixid=eyJhcHBfaWQiOjYyMDE0fQ",
            "small": "https://images.unsplash.com/photo-1522030865324-4062412a2023?ixlib=rb-1.2.1&q=80&fm=jpg&crop=entropy&cs=tinysrgb&w=400&fit=max&ixid=eyJhcHBfaWQiOjYyMDE0fQ",
            "thumb": "https://images.unsplash.com/photo-1522030865324-4062412a2023?ixlib=rb-1.2.1&q=80&fm=jpg&crop=entropy&cs=tinysrgb&w=200&fit=max&ixid=eyJhcHBfaWQiOjYyMDE0fQ"
         },
         "links": {
            "self": "https://api.unsplash.com/photos/AVzByhROPbs",
            "html": "https://unsplash.com/photos/AVzByhROPbs",
            "download": "https://unsplash.com/photos/AVzByhROPbs/download",
            "download_location": "https://api.unsplash.com/photos/AVzByhROPbs/download"
         },
         "user": "lastly",
         "tags": ["flora", "jar", "plant"],
         "downloaded": false
      },
      {
         "id": "IBPgeshzHvs",
         "description": "View from the car during the heavy rain",
         "urls": {
            "raw": "https://images.unsplash.com/photo-1473304359707-d6059a32cf1d?ixlib=rb-1.2.1&ixid=eyJhcHBfaWQiOjYyMDE0fQ",
            "full": "https://images.unsplash.com/photo-1473304359707-d6059a32cf1d?ixlib=rb-1.2.1&q=85&fm=jpg&crop=entropy&cs=srgb&ixid=eyJhcHBfaWQiOjYyMDE0fQ",
            "regular": "https://images.unsplash.com/photo-1473304359707-d6059a32cf1d?ixlib=rb-1.2.1&q=80&fm=jpg&crop=entropy&cs=tinysrgb&w=1080&fit=max&ixid=eyJhcHBfaWQiOjYyMDE0fQ",
            "small": "https://images.unsplash.com/photo-1473304359707-d6059a32cf1d?ixlib=rb-1.2.1&q=80&fm=jpg&crop=entropy&cs=tinysrgb&w=400&fit=max&ixid=eyJhcHBfaWQiOjYyMDE0fQ",
            "thumb": "https://images.unsplash.com/photo-1473304359707-d6059a32cf1d?ixlib=rb-1.2.1&q=80&fm=jpg&crop=entropy&cs=tinysrgb&w=200&fit=max&ixid=eyJhcHBfaWQiOjYyMDE0fQ"
         },
         "links": {
            "self": "https://api.unsplash.com/photos/IBPgeshzHvs",
            "html": "https://unsplash.com/photos/IBPgeshzHvs",
            "download": "https://unsplash.com/photos/IBPgeshzHvs/download",
            "download_location": "https://api.unsplash.com/photos/IBPgeshzHvs/download"
         },
         "user": "charliedeets",
         "tags": ["rain", "car", "highway"],
         "downloaded": false
      },
      {
         "id": "wESKMSgZJDo",
         "description": "female head from behind",
         "urls": {
            "raw": "https://images.unsplash.com/reserve/wVlfnlTbRtK8eGvbnBZI_VolkanOlmez_005.jpg?ixlib=rb-1.2.1&ixid=eyJhcHBfaWQiOjYyMDE0fQ",
            "full": "https://images.unsplash.com/reserve/wVlfnlTbRtK8eGvbnBZI_VolkanOlmez_005.jpg?ixlib=rb-1.2.1&q=85&fm=jpg&crop=entropy&cs=srgb&ixid=eyJhcHBfaWQiOjYyMDE0fQ",
            "regular": "https://images.unsplash.com/reserve/wVlfnlTbRtK8eGvbnBZI_VolkanOlmez_005.jpg?ixlib=rb-1.2.1&q=80&fm=jpg&crop=entropy&cs=tinysrgb&w=1080&fit=max&ixid=eyJhcHBfaWQiOjYyMDE0fQ",
            "small": "https://images.unsplash.com/reserve/wVlfnlTbRtK8eGvbnBZI_VolkanOlmez_005.jpg?ixlib=rb-1.2.1&q=80&fm=jpg&crop=entropy&cs=tinysrgb&w=400&fit=max&ixid=eyJhcHBfaWQiOjYyMDE0fQ",
            "thumb": "https://images.unsplash.com/reserve/wVlfnlTbRtK8eGvbnBZI_VolkanOlmez_005.jpg?ixlib=rb-1.2.1&q=80&fm=jpg&crop=entropy&cs=tinysrgb&w=200&fit=max&ixid=eyJhcHBfaWQiOjYyMDE0fQ"
         },
         "links": {
            "self": "https://api.unsplash.com/photos/wESKMSgZJDo",
            "html": "https://unsplash.com/photos/wESKMSgZJDo",
            "download": "https://unsplash.com/photos/wESKMSgZJDo/download",
            "download_location": "https://api.unsplash.com/photos/wESKMSgZJDo/download"
         },
         "user": "volkanolmez",
         "tags": ["grey", "black-and-white", "people"],
         "downloaded": false
      },
      {
         "id": "IQNbNtvC4XE",
         "description": null,
         "urls": {
            "raw": "https://images.unsplash.com/photo-1476189297164-5f6da5eddd23?ixlib=rb-1.2.1&ixid=eyJhcHBfaWQiOjYyMDE0fQ",
            "full": "https://images.unsplash.com/photo-1476189297164-5f6da5eddd23?ixlib=rb-1.2.1&q=85&fm=jpg&crop=entropy&cs=srgb&ixid=eyJhcHBfaWQiOjYyMDE0fQ",
            "regular": "https://images.unsplash.com/photo-1476189297164-5f6da5eddd23?ixlib=rb-1.2.1&q=80&fm=jpg&crop=entropy&cs=tinysrgb&w=1080&fit=max&ixid=eyJhcHBfaWQiOjYyMDE0fQ",
            "small": "https://images.unsplash.com/photo-1476189297164-5f6da5eddd23?ixlib=rb-1.2.1&q=80&fm=jpg&crop=entropy&cs=tinysrgb&w=400&fit=max&ixid=eyJhcHBfaWQiOjYyMDE0fQ",
            "thumb": "https://images.unsplash.com/photo-1476189297164-5f6da5eddd23?ixlib=rb-1.2.1&q=80&fm=jpg&crop=entropy&cs=tinysrgb&w=200&fit=max&ixid=eyJhcHBfaWQiOjYyMDE0fQ"
         },
         "links": {
            "self": "https://api.unsplash.com/photos/IQNbNtvC4XE",
            "html": "https://unsplash.com/photos/IQNbNtvC4XE",
            "download": "https://unsplash.com/photos/IQNbNtvC4XE/download",
            "download_location": "https://api.unsplash.com/photos/IQNbNtvC4XE/download"
         },
         "user": "jack_scorner",
         "tags": ["dock", "pier", "water front"],
         "downloaded": false
      },
      {
         "id": "tLDeO8lTgII",
         "description": "Fog on Mountain",
         "urls": {
            "raw": "https://images.unsplash.com/photo-1497216429614-5bd7dbd9fc48?ixlib=rb-1.2.1&ixid=eyJhcHBfaWQiOjYyMDE0fQ",
            "full": "https://images.unsplash.com/photo-1497216429614-5bd7dbd9fc48?ixlib=rb-1.2.1&q=85&fm=jpg&crop=entropy&cs=srgb&ixid=eyJhcHBfaWQiOjYyMDE0fQ",
            "regular": "https://images.unsplash.com/photo-1497216429614-5bd7dbd9fc48?ixlib=rb-1.2.1&q=80&fm=jpg&crop=entropy&cs=tinysrgb&w=1080&fit=max&ixid=eyJhcHBfaWQiOjYyMDE0fQ",
            "small": "https://images.unsplash.com/photo-1497216429614-5bd7dbd9fc48?ixlib=rb-1.2.1&q=80&fm=jpg&crop=entropy&cs=tinysrgb&w=400&fit=max&ixid=eyJhcHBfaWQiOjYyMDE0fQ",
            "thumb": "https://images.unsplash.com/photo-1497216429614-5bd7dbd9fc48?ixlib=rb-1.2.1&q=80&fm=jpg&crop=entropy&cs=tinysrgb&w=200&fit=max&ixid=eyJhcHBfaWQiOjYyMDE0fQ"
         },
         "links": {
            "self": "https://api.unsplash.com/photos/tLDeO8lTgII",
            "html": "https://unsplash.com/photos/tLDeO8lTgII",
            "download": "https://unsplash.com/photos/tLDeO8lTgII/download",
            "download_location": "https://api.unsplash.com/photos/tLDeO8lTgII/download"
         },
         "user": "woods",
         "tags": ["highway", "road", "freeway"],
         "downloaded": false
      },
      {
         "id": "OZSNnAU5RPk",
         "description": null,
         "urls": {
            "raw": "https://images.unsplash.com/photo-1436476426006-344b576bd5d4?ixlib=rb-1.2.1&ixid=eyJhcHBfaWQiOjYyMDE0fQ",
            "full": "https://images.unsplash.com/photo-1436476426006-344b576bd5d4?ixlib=rb-1.2.1&q=85&fm=jpg&crop=entropy&cs=srgb&ixid=eyJhcHBfaWQiOjYyMDE0fQ",
            "regular": "https://images.unsplash.com/photo-1436476426006-344b576bd5d4?ixlib=rb-1.2.1&q=80&fm=jpg&crop=entropy&cs=tinysrgb&w=1080&fit=max&ixid=eyJhcHBfaWQiOjYyMDE0fQ",
            "small": "https://images.unsplash.com/photo-1436476426006-344b576bd5d4?ixlib=rb-1.2.1&q=80&fm=jpg&crop=entropy&cs=tinysrgb&w=400&fit=max&ixid=eyJhcHBfaWQiOjYyMDE0fQ",
            "thumb": "https://images.unsplash.com/photo-1436476426006-344b576bd5d4?ixlib=rb-1.2.1&q=80&fm=jpg&crop=entropy&cs=tinysrgb&w=200&fit=max&ixid=eyJhcHBfaWQiOjYyMDE0fQ"
         },
         "links": {
            "self": "https://api.unsplash.com/photos/OZSNnAU5RPk",
            "html": "https://unsplash.com/photos/OZSNnAU5RPk",
            "download": "https://unsplash.com/photos/OZSNnAU5RPk/download",
            "download_location": "https://api.unsplash.com/photos/OZSNnAU5RPk/download"
         },
         "user": "aaronalvaradophotography",
         "tags": ["forest", "tree", "moody"],
         "downloaded": false
      },
      {
         "id": "JBfdCFeRDeQ",
         "description": null,
         "urls": {
            "raw": "https://images.unsplash.com/photo-1474031317822-f51f48735ddd?ixlib=rb-1.2.1&ixid=eyJhcHBfaWQiOjYyMDE0fQ",
            "full": "https://images.unsplash.com/photo-1474031317822-f51f48735ddd?ixlib=rb-1.2.1&q=85&fm=jpg&crop=entropy&cs=srgb&ixid=eyJhcHBfaWQiOjYyMDE0fQ",
            "regular": "https://images.unsplash.com/photo-1474031317822-f51f48735ddd?ixlib=rb-1.2.1&q=80&fm=jpg&crop=entropy&cs=tinysrgb&w=1080&fit=max&ixid=eyJhcHBfaWQiOjYyMDE0fQ",
            "small": "https://images.unsplash.com/photo-1474031317822-f51f48735ddd?ixlib=rb-1.2.1&q=80&fm=jpg&crop=entropy&cs=tinysrgb&w=400&fit=max&ixid=eyJhcHBfaWQiOjYyMDE0fQ",
            "thumb": "https://images.unsplash.com/photo-1474031317822-f51f48735ddd?ixlib=rb-1.2.1&q=80&fm=jpg&crop=entropy&cs=tinysrgb&w=200&fit=max&ixid=eyJhcHBfaWQiOjYyMDE0fQ"
         },
         "links": {
            "self": "https://api.unsplash.com/photos/JBfdCFeRDeQ",
            "html": "https://unsplash.com/photos/JBfdCFeRDeQ",
            "download": "https://unsplash.com/photos/JBfdCFeRDeQ/download",
            "download_location": "https://api.unsplash.com/photos/JBfdCFeRDeQ/download"
         },
         "user": "andrewtneel",
         "tags": ["grey", "people", "person"],
         "downloaded": false
      },
      {
         "id": "evJtqVB7jdY",
         "description": "Even before I submitted my first photo in Unsplash, I always used to look at these epic misty forest shots with awe. Then I managed to do my own. Heck, my most popular is one of them. Sometimes we set our own limits and we become our own worst enemies. The past 4-5 years of my life, it became very clear to me that one has to define his own life. Push boundaries, try the unthinkable and challenge one’s self. \r\n\r\nP.S. I love misty forest shots.",
         "urls": {
            "raw": "https://images.unsplash.com/photo-1486327764279-9ad06d206d9f?ixlib=rb-1.2.1&ixid=eyJhcHBfaWQiOjYyMDE0fQ",
            "full": "https://images.unsplash.com/photo-1486327764279-9ad06d206d9f?ixlib=rb-1.2.1&q=85&fm=jpg&crop=entropy&cs=srgb&ixid=eyJhcHBfaWQiOjYyMDE0fQ",
            "regular": "https://images.unsplash.com/photo-1486327764279-9ad06d206d9f?ixlib=rb-1.2.1&q=80&fm=jpg&crop=entropy&cs=tinysrgb&w=1080&fit=max&ixid=eyJhcHBfaWQiOjYyMDE0fQ",
            "small": "https://images.unsplash.com/photo-1486327764279-9ad06d206d9f?ixlib=rb-1.2.1&q=80&fm=jpg&crop=entropy&cs=tinysrgb&w=400&fit=max&ixid=eyJhcHBfaWQiOjYyMDE0fQ",
            "thumb": "https://images.unsplash.com/photo-1486327764279-9ad06d206d9f?ixlib=rb-1.2.1&q=80&fm=jpg&crop=entropy&cs=tinysrgb&w=200&fit=max&ixid=eyJhcHBfaWQiOjYyMDE0fQ"
         },
         "links": {
            "self": "https://api.unsplash.com/photos/evJtqVB7jdY",
            "html": "https://unsplash.com/photos/evJtqVB7jdY",
            "download": "https://unsplash.com/photos/evJtqVB7jdY/download",
            "download_location": "https://api.unsplash.com/photos/evJtqVB7jdY/download"
         },
         "user": "paulgilmore_",
         "tags": ["forest", "moody", "mist"],
         "downloaded": false
      },
      {
         "id": "9ZmclZb_ca8",
         "description": null,
         "urls": {
            "raw": "https://images.unsplash.com/photo-1486868339192-0a82341f8b87?ixlib=rb-1.2.1&ixid=eyJhcHBfaWQiOjYyMDE0fQ",
            "full": "https://images.unsplash.com/photo-1486868339192-0a82341f8b87?ixlib=rb-1.2.1&q=85&fm=jpg&crop=entropy&cs=srgb&ixid=eyJhcHBfaWQiOjYyMDE0fQ",
            "regular": "https://images.unsplash.com/photo-1486868339192-0a82341f8b87?ixlib=rb-1.2.1&q=80&fm=jpg&crop=entropy&cs=tinysrgb&w=1080&fit=max&ixid=eyJhcHBfaWQiOjYyMDE0fQ",
            "small": "https://images.unsplash.com/photo-1486868339192-0a82341f8b87?ixlib=rb-1.2.1&q=80&fm=jpg&crop=entropy&cs=tinysrgb&w=400&fit=max&ixid=eyJhcHBfaWQiOjYyMDE0fQ",
            "thumb": "https://images.unsplash.com/photo-1486868339192-0a82341f8b87?ixlib=rb-1.2.1&q=80&fm=jpg&crop=entropy&cs=tinysrgb&w=200&fit=max&ixid=eyJhcHBfaWQiOjYyMDE0fQ"
         },
         "links": {
            "self": "https://api.unsplash.com/photos/9ZmclZb_ca8",
            "html": "https://unsplash.com/photos/9ZmclZb_ca8",
            "download": "https://unsplash.com/photos/9ZmclZb_ca8/download",
            "download_location": "https://api.unsplash.com/photos/9ZmclZb_ca8/download"
         },
         "user": "nathananderson",
         "tags": ["mountain range", "peak", "mountain"],
         "downloaded": false
      },
      {
         "id": "OZ-KfZPb91c",
         "description": "Lost at sea",
         "urls": {
            "raw": "https://images.unsplash.com/photo-1497749334368-9a978ae92b71?ixlib=rb-1.2.1&ixid=eyJhcHBfaWQiOjYyMDE0fQ",
            "full": "https://images.unsplash.com/photo-1497749334368-9a978ae92b71?ixlib=rb-1.2.1&q=85&fm=jpg&crop=entropy&cs=srgb&ixid=eyJhcHBfaWQiOjYyMDE0fQ",
            "regular": "https://images.unsplash.com/photo-1497749334368-9a978ae92b71?ixlib=rb-1.2.1&q=80&fm=jpg&crop=entropy&cs=tinysrgb&w=1080&fit=max&ixid=eyJhcHBfaWQiOjYyMDE0fQ",
            "small": "https://images.unsplash.com/photo-1497749334368-9a978ae92b71?ixlib=rb-1.2.1&q=80&fm=jpg&crop=entropy&cs=tinysrgb&w=400&fit=max&ixid=eyJhcHBfaWQiOjYyMDE0fQ",
            "thumb": "https://images.unsplash.com/photo-1497749334368-9a978ae92b71?ixlib=rb-1.2.1&q=80&fm=jpg&crop=entropy&cs=tinysrgb&w=200&fit=max&ixid=eyJhcHBfaWQiOjYyMDE0fQ"
         },
         "links": {
            "self": "https://api.unsplash.com/photos/OZ-KfZPb91c",
            "html": "https://unsplash.com/photos/OZ-KfZPb91c",
            "download": "https://unsplash.com/photos/OZ-KfZPb91c/download",
            "download_location": "https://api.unsplash.com/photos/OZ-KfZPb91c/download"
         },
         "user": "christopher__burns",
         "tags": ["moody", "lighthouse", "coastal"],
         "downloaded": false
      },
      {
         "id": "uDUiRS8YroY",
         "description": "monochrome pier with sky",
         "urls": {
            "raw": "https://images.unsplash.com/5/pier.JPG?ixlib=rb-1.2.1&ixid=eyJhcHBfaWQiOjYyMDE0fQ",
            "full": "https://images.unsplash.com/5/pier.JPG?ixlib=rb-1.2.1&q=85&fm=jpg&crop=entropy&cs=srgb&ixid=eyJhcHBfaWQiOjYyMDE0fQ",
            "regular": "https://images.unsplash.com/5/pier.JPG?ixlib=rb-1.2.1&q=80&fm=jpg&crop=entropy&cs=tinysrgb&w=1080&fit=max&ixid=eyJhcHBfaWQiOjYyMDE0fQ",
            "small": "https://images.unsplash.com/5/pier.JPG?ixlib=rb-1.2.1&q=80&fm=jpg&crop=entropy&cs=tinysrgb&w=400&fit=max&ixid=eyJhcHBfaWQiOjYyMDE0fQ",
            "thumb": "https://images.unsplash.com/5/pier.JPG?ixlib=rb-1.2.1&q=80&fm=jpg&crop=entropy&cs=tinysrgb&w=200&fit=max&ixid=eyJhcHBfaWQiOjYyMDE0fQ"
         },
         "links": {
            "self": "https://api.unsplash.com/photos/uDUiRS8YroY",
            "html": "https://unsplash.com/photos/uDUiRS8YroY",
            "download": "https://unsplash.com/photos/uDUiRS8YroY/download",
            "download_location": "https://api.unsplash.com/photos/uDUiRS8YroY/download"
         },
         "user": "css",
         "tags": ["black-and-white", "dock", "pier"],
         "downloaded": false
      },
      {
         "id": "dC5YbKG2Qks",
         "description": "I see my path, but I don’t know where it leads. Not knowing where I’m going is what inspires me to travel it.\r\n— Rosalia de Castro",
         "urls": {
            "raw": "https://images.unsplash.com/photo-1492500318351-274a118407c2?ixlib=rb-1.2.1&ixid=eyJhcHBfaWQiOjYyMDE0fQ",
            "full": "https://images.unsplash.com/photo-1492500318351-274a118407c2?ixlib=rb-1.2.1&q=85&fm=jpg&crop=entropy&cs=srgb&ixid=eyJhcHBfaWQiOjYyMDE0fQ",
            "regular": "https://images.unsplash.com/photo-1492500318351-274a118407c2?ixlib=rb-1.2.1&q=80&fm=jpg&crop=entropy&cs=tinysrgb&w=1080&fit=max&ixid=eyJhcHBfaWQiOjYyMDE0fQ",
            "small": "https://images.unsplash.com/photo-1492500318351-274a118407c2?ixlib=rb-1.2.1&q=80&fm=jpg&crop=entropy&cs=tinysrgb&w=400&fit=max&ixid=eyJhcHBfaWQiOjYyMDE0fQ",
            "thumb": "https://images.unsplash.com/photo-1492500318351-274a118407c2?ixlib=rb-1.2.1&q=80&fm=jpg&crop=entropy&cs=tinysrgb&w=200&fit=max&ixid=eyJhcHBfaWQiOjYyMDE0fQ"
         },
         "links": {
            "self": "https://api.unsplash.com/photos/dC5YbKG2Qks",
            "html": "https://unsplash.com/photos/dC5YbKG2Qks",
            "download": "https://unsplash.com/photos/dC5YbKG2Qks/download",
            "download_location": "https://api.unsplash.com/photos/dC5YbKG2Qks/download"
         },
         "user": "andrewtneel",
         "tags": ["road", "dirt road", "stone mountain state park"],
         "downloaded": false
      },
      {
         "id": "DsIpNh9s5qc",
         "description": null,
         "urls": {
            "raw": "https://images.unsplash.com/photo-1442530789823-1efd606eef25?ixlib=rb-1.2.1&ixid=eyJhcHBfaWQiOjYyMDE0fQ",
            "full": "https://images.unsplash.com/photo-1442530789823-1efd606eef25?ixlib=rb-1.2.1&q=85&fm=jpg&crop=entropy&cs=srgb&ixid=eyJhcHBfaWQiOjYyMDE0fQ",
            "regular": "https://images.unsplash.com/photo-1442530789823-1efd606eef25?ixlib=rb-1.2.1&q=80&fm=jpg&crop=entropy&cs=tinysrgb&w=1080&fit=max&ixid=eyJhcHBfaWQiOjYyMDE0fQ",
            "small": "https://images.unsplash.com/photo-1442530789823-1efd606eef25?ixlib=rb-1.2.1&q=80&fm=jpg&crop=entropy&cs=tinysrgb&w=400&fit=max&ixid=eyJhcHBfaWQiOjYyMDE0fQ",
            "thumb": "https://images.unsplash.com/photo-1442530789823-1efd606eef25?ixlib=rb-1.2.1&q=80&fm=jpg&crop=entropy&cs=tinysrgb&w=200&fit=max&ixid=eyJhcHBfaWQiOjYyMDE0fQ"
         },
         "links": {
            "self": "https://api.unsplash.com/photos/DsIpNh9s5qc",
            "html": "https://unsplash.com/photos/DsIpNh9s5qc",
            "download": "https://unsplash.com/photos/DsIpNh9s5qc/download",
            "download_location": "https://api.unsplash.com/photos/DsIpNh9s5qc/download"
         },
         "user": "jannelle_althoff",
         "tags": ["mountain", "nature", "cloud"],
         "downloaded": false
      },
      {
         "id": "ndbyw7oNI7Y",
         "description": "Fading horizons.",
         "urls": {
            "raw": "https://images.unsplash.com/photo-1494694081617-38b4cba8fc36?ixlib=rb-1.2.1&ixid=eyJhcHBfaWQiOjYyMDE0fQ",
            "full": "https://images.unsplash.com/photo-1494694081617-38b4cba8fc36?ixlib=rb-1.2.1&q=85&fm=jpg&crop=entropy&cs=srgb&ixid=eyJhcHBfaWQiOjYyMDE0fQ",
            "regular": "https://images.unsplash.com/photo-1494694081617-38b4cba8fc36?ixlib=rb-1.2.1&q=80&fm=jpg&crop=entropy&cs=tinysrgb&w=1080&fit=max&ixid=eyJhcHBfaWQiOjYyMDE0fQ",
            "small": "https://images.unsplash.com/photo-1494694081617-38b4cba8fc36?ixlib=rb-1.2.1&q=80&fm=jpg&crop=entropy&cs=tinysrgb&w=400&fit=max&ixid=eyJhcHBfaWQiOjYyMDE0fQ",
            "thumb": "https://images.unsplash.com/photo-1494694081617-38b4cba8fc36?ixlib=rb-1.2.1&q=80&fm=jpg&crop=entropy&cs=tinysrgb&w=200&fit=max&ixid=eyJhcHBfaWQiOjYyMDE0fQ"
         },
         "links": {
            "self": "https://api.unsplash.com/photos/ndbyw7oNI7Y",
            "html": "https://unsplash.com/photos/ndbyw7oNI7Y",
            "download": "https://unsplash.com/photos/ndbyw7oNI7Y/download",
            "download_location": "https://api.unsplash.com/photos/ndbyw7oNI7Y/download"
         },
         "user": "ameenfahmy_",
         "tags": ["grey", "ocean", "sea"],
         "downloaded": false
      },
      {
         "id": "U9fBPG9jZeY",
         "description": "Desolate Bridge",
         "urls": {
            "raw": "https://images.unsplash.com/photo-1480258350533-dee0cede28e1?ixlib=rb-1.2.1&ixid=eyJhcHBfaWQiOjYyMDE0fQ",
            "full": "https://images.unsplash.com/photo-1480258350533-dee0cede28e1?ixlib=rb-1.2.1&q=85&fm=jpg&crop=entropy&cs=srgb&ixid=eyJhcHBfaWQiOjYyMDE0fQ",
            "regular": "https://images.unsplash.com/photo-1480258350533-dee0cede28e1?ixlib=rb-1.2.1&q=80&fm=jpg&crop=entropy&cs=tinysrgb&w=1080&fit=max&ixid=eyJhcHBfaWQiOjYyMDE0fQ",
            "small": "https://images.unsplash.com/photo-1480258350533-dee0cede28e1?ixlib=rb-1.2.1&q=80&fm=jpg&crop=entropy&cs=tinysrgb&w=400&fit=max&ixid=eyJhcHBfaWQiOjYyMDE0fQ",
            "thumb": "https://images.unsplash.com/photo-1480258350533-dee0cede28e1?ixlib=rb-1.2.1&q=80&fm=jpg&crop=entropy&cs=tinysrgb&w=200&fit=max&ixid=eyJhcHBfaWQiOjYyMDE0fQ"
         },
         "links": {
            "self": "https://api.unsplash.com/photos/U9fBPG9jZeY",
            "html": "https://unsplash.com/photos/U9fBPG9jZeY",
            "download": "https://unsplash.com/photos/U9fBPG9jZeY/download",
            "download_location": "https://api.unsplash.com/photos/U9fBPG9jZeY/download"
         },
         "user": "grounded",
         "tags": ["mist", "cloud", "bridge"],
         "downloaded": false
      },
      {
         "id": "mScyalv6BTQ",
         "description": null,
         "urls": {
            "raw": "https://images.unsplash.com/photo-1473157548731-112b3b175783?ixlib=rb-1.2.1&ixid=eyJhcHBfaWQiOjYyMDE0fQ",
            "full": "https://images.unsplash.com/photo-1473157548731-112b3b175783?ixlib=rb-1.2.1&q=85&fm=jpg&crop=entropy&cs=srgb&ixid=eyJhcHBfaWQiOjYyMDE0fQ",
            "regular": "https://images.unsplash.com/photo-1473157548731-112b3b175783?ixlib=rb-1.2.1&q=80&fm=jpg&crop=entropy&cs=tinysrgb&w=1080&fit=max&ixid=eyJhcHBfaWQiOjYyMDE0fQ",
            "small": "https://images.unsplash.com/photo-1473157548731-112b3b175783?ixlib=rb-1.2.1&q=80&fm=jpg&crop=entropy&cs=tinysrgb&w=400&fit=max&ixid=eyJhcHBfaWQiOjYyMDE0fQ",
            "thumb": "https://images.unsplash.com/photo-1473157548731-112b3b175783?ixlib=rb-1.2.1&q=80&fm=jpg&crop=entropy&cs=tinysrgb&w=200&fit=max&ixid=eyJhcHBfaWQiOjYyMDE0fQ"
         },
         "links": {
            "self": "https://api.unsplash.com/photos/mScyalv6BTQ",
            "html": "https://unsplash.com/photos/mScyalv6BTQ",
            "download": "https://unsplash.com/photos/mScyalv6BTQ/download",
            "download_location": "https://api.unsplash.com/photos/mScyalv6BTQ/download"
         },
         "user": "samvimes",
         "tags": ["mountain", "nature", "clouds"],
         "downloaded": false
      },
      {
         "id": "a_xa7RUKzdc",
         "description": null,
         "urls": {
            "raw": "https://images.unsplash.com/reserve/IPEivX6xSBaiYOukY88V_DSC06462_tonemapped.jpg?ixlib=rb-1.2.1&ixid=eyJhcHBfaWQiOjYyMDE0fQ",
            "full": "https://images.unsplash.com/reserve/IPEivX6xSBaiYOukY88V_DSC06462_tonemapped.jpg?ixlib=rb-1.2.1&q=85&fm=jpg&crop=entropy&cs=srgb&ixid=eyJhcHBfaWQiOjYyMDE0fQ",
            "regular": "https://images.unsplash.com/reserve/IPEivX6xSBaiYOukY88V_DSC06462_tonemapped.jpg?ixlib=rb-1.2.1&q=80&fm=jpg&crop=entropy&cs=tinysrgb&w=1080&fit=max&ixid=eyJhcHBfaWQiOjYyMDE0fQ",
            "small": "https://images.unsplash.com/reserve/IPEivX6xSBaiYOukY88V_DSC06462_tonemapped.jpg?ixlib=rb-1.2.1&q=80&fm=jpg&crop=entropy&cs=tinysrgb&w=400&fit=max&ixid=eyJhcHBfaWQiOjYyMDE0fQ",
            "thumb": "https://images.unsplash.com/reserve/IPEivX6xSBaiYOukY88V_DSC06462_tonemapped.jpg?ixlib=rb-1.2.1&q=80&fm=jpg&crop=entropy&cs=tinysrgb&w=200&fit=max&ixid=eyJhcHBfaWQiOjYyMDE0fQ"
         },
         "links": {
            "self": "https://api.unsplash.com/photos/a_xa7RUKzdc",
            "html": "https://unsplash.com/photos/a_xa7RUKzdc",
            "download": "https://unsplash.com/photos/a_xa7RUKzdc/download",
            "download_location": "https://api.unsplash.com/photos/a_xa7RUKzdc/download"
         },
         "user": "benjaminslothlindgreen",
         "tags": ["road", "clouds", "hills"],
         "downloaded": false
      },
      {
         "id": "IHctIAJK7aw",
         "description": "Woods on a rocky hill",
         "urls": {
            "raw": "https://images.unsplash.com/photo-1422225933358-6e117a2758e3?ixlib=rb-1.2.1&ixid=eyJhcHBfaWQiOjYyMDE0fQ",
            "full": "https://images.unsplash.com/photo-1422225933358-6e117a2758e3?ixlib=rb-1.2.1&q=85&fm=jpg&crop=entropy&cs=srgb&ixid=eyJhcHBfaWQiOjYyMDE0fQ",
            "regular": "https://images.unsplash.com/photo-1422225933358-6e117a2758e3?ixlib=rb-1.2.1&q=80&fm=jpg&crop=entropy&cs=tinysrgb&w=1080&fit=max&ixid=eyJhcHBfaWQiOjYyMDE0fQ",
            "small": "https://images.unsplash.com/photo-1422225933358-6e117a2758e3?ixlib=rb-1.2.1&q=80&fm=jpg&crop=entropy&cs=tinysrgb&w=400&fit=max&ixid=eyJhcHBfaWQiOjYyMDE0fQ",
            "thumb": "https://images.unsplash.com/photo-1422225933358-6e117a2758e3?ixlib=rb-1.2.1&q=80&fm=jpg&crop=entropy&cs=tinysrgb&w=200&fit=max&ixid=eyJhcHBfaWQiOjYyMDE0fQ"
         },
         "links": {
            "self": "https://api.unsplash.com/photos/IHctIAJK7aw",
            "html": "https://unsplash.com/photos/IHctIAJK7aw",
            "download": "https://unsplash.com/photos/IHctIAJK7aw/download",
            "download_location": "https://api.unsplash.com/photos/IHctIAJK7aw/download"
         },
         "user": "flegontovna",
         "tags": ["forest", "tree", "nature"],
         "downloaded": false
      },
      {
         "id": "ewslNYDXmT8",
         "description": null,
         "urls": {
            "raw": "https://images.unsplash.com/photo-1415857221319-ec25f9d00899?ixlib=rb-1.2.1&ixid=eyJhcHBfaWQiOjYyMDE0fQ",
            "full": "https://images.unsplash.com/photo-1415857221319-ec25f9d00899?ixlib=rb-1.2.1&q=85&fm=jpg&crop=entropy&cs=srgb&ixid=eyJhcHBfaWQiOjYyMDE0fQ",
            "regular": "https://images.unsplash.com/photo-1415857221319-ec25f9d00899?ixlib=rb-1.2.1&q=80&fm=jpg&crop=entropy&cs=tinysrgb&w=1080&fit=max&ixid=eyJhcHBfaWQiOjYyMDE0fQ",
            "small": "https://images.unsplash.com/photo-1415857221319-ec25f9d00899?ixlib=rb-1.2.1&q=80&fm=jpg&crop=entropy&cs=tinysrgb&w=400&fit=max&ixid=eyJhcHBfaWQiOjYyMDE0fQ",
            "thumb": "https://images.unsplash.com/photo-1415857221319-ec25f9d00899?ixlib=rb-1.2.1&q=80&fm=jpg&crop=entropy&cs=tinysrgb&w=200&fit=max&ixid=eyJhcHBfaWQiOjYyMDE0fQ"
         },
         "links": {
            "self": "https://api.unsplash.com/photos/ewslNYDXmT8",
            "html": "https://unsplash.com/photos/ewslNYDXmT8",
            "download": "https://unsplash.com/photos/ewslNYDXmT8/download",
            "download_location": "https://api.unsplash.com/photos/ewslNYDXmT8/download"
         },
         "user": "milo_m",
         "tags": ["ocean", "sea", "coast"],
         "downloaded": false
      },
      {
         "id": "f04IRgkV1AM",
         "description": "Here comes the storm",
         "urls": {
            "raw": "https://images.unsplash.com/photo-1491381198954-1a8579b28b22?ixlib=rb-1.2.1&ixid=eyJhcHBfaWQiOjYyMDE0fQ",
            "full": "https://images.unsplash.com/photo-1491381198954-1a8579b28b22?ixlib=rb-1.2.1&q=85&fm=jpg&crop=entropy&cs=srgb&ixid=eyJhcHBfaWQiOjYyMDE0fQ",
            "regular": "https://images.unsplash.com/photo-1491381198954-1a8579b28b22?ixlib=rb-1.2.1&q=80&fm=jpg&crop=entropy&cs=tinysrgb&w=1080&fit=max&ixid=eyJhcHBfaWQiOjYyMDE0fQ",
            "small": "https://images.unsplash.com/photo-1491381198954-1a8579b28b22?ixlib=rb-1.2.1&q=80&fm=jpg&crop=entropy&cs=tinysrgb&w=400&fit=max&ixid=eyJhcHBfaWQiOjYyMDE0fQ",
            "thumb": "https://images.unsplash.com/photo-1491381198954-1a8579b28b22?ixlib=rb-1.2.1&q=80&fm=jpg&crop=entropy&cs=tinysrgb&w=200&fit=max&ixid=eyJhcHBfaWQiOjYyMDE0fQ"
         },
         "links": {
            "self": "https://api.unsplash.com/photos/f04IRgkV1AM",
            "html": "https://unsplash.com/photos/f04IRgkV1AM",
            "download": "https://unsplash.com/photos/f04IRgkV1AM/download",
            "download_location": "https://api.unsplash.com/photos/f04IRgkV1AM/download"
         },
         "user": "timmarshall",
         "tags": ["ocean", "sea", "water"],
         "downloaded": false
      },
      {
         "id": "cjpGSEkXfwM",
         "description": "Saint Like",
         "urls": {
            "raw": "https://images.unsplash.com/photo-1499482624510-89fb8b6d0ded?ixlib=rb-1.2.1&ixid=eyJhcHBfaWQiOjYyMDE0fQ",
            "full": "https://images.unsplash.com/photo-1499482624510-89fb8b6d0ded?ixlib=rb-1.2.1&q=85&fm=jpg&crop=entropy&cs=srgb&ixid=eyJhcHBfaWQiOjYyMDE0fQ",
            "regular": "https://images.unsplash.com/photo-1499482624510-89fb8b6d0ded?ixlib=rb-1.2.1&q=80&fm=jpg&crop=entropy&cs=tinysrgb&w=1080&fit=max&ixid=eyJhcHBfaWQiOjYyMDE0fQ",
            "small": "https://images.unsplash.com/photo-1499482624510-89fb8b6d0ded?ixlib=rb-1.2.1&q=80&fm=jpg&crop=entropy&cs=tinysrgb&w=400&fit=max&ixid=eyJhcHBfaWQiOjYyMDE0fQ",
            "thumb": "https://images.unsplash.com/photo-1499482624510-89fb8b6d0ded?ixlib=rb-1.2.1&q=80&fm=jpg&crop=entropy&cs=tinysrgb&w=200&fit=max&ixid=eyJhcHBfaWQiOjYyMDE0fQ"
         },
         "links": {
            "self": "https://api.unsplash.com/photos/cjpGSEkXfwM",
            "html": "https://unsplash.com/photos/cjpGSEkXfwM",
            "download": "https://unsplash.com/photos/cjpGSEkXfwM/download",
            "download_location": "https://api.unsplash.com/photos/cjpGSEkXfwM/download"
         },
         "user": "jasonhk1920",
         "tags": ["city", "silhouette", "building"],
         "downloaded": false
      },
      {
         "id": "xxWU76ALQE8",
         "description": "Dark sunset over Boundary Waters",
         "urls": {
            "raw": "https://images.unsplash.com/photo-1470681151804-311e1b738c23?ixlib=rb-1.2.1&ixid=eyJhcHBfaWQiOjYyMDE0fQ",
            "full": "https://images.unsplash.com/photo-1470681151804-311e1b738c23?ixlib=rb-1.2.1&q=85&fm=jpg&crop=entropy&cs=srgb&ixid=eyJhcHBfaWQiOjYyMDE0fQ",
            "regular": "https://images.unsplash.com/photo-1470681151804-311e1b738c23?ixlib=rb-1.2.1&q=80&fm=jpg&crop=entropy&cs=tinysrgb&w=1080&fit=max&ixid=eyJhcHBfaWQiOjYyMDE0fQ",
            "small": "https://images.unsplash.com/photo-1470681151804-311e1b738c23?ixlib=rb-1.2.1&q=80&fm=jpg&crop=entropy&cs=tinysrgb&w=400&fit=max&ixid=eyJhcHBfaWQiOjYyMDE0fQ",
            "thumb": "https://images.unsplash.com/photo-1470681151804-311e1b738c23?ixlib=rb-1.2.1&q=80&fm=jpg&crop=entropy&cs=tinysrgb&w=200&fit=max&ixid=eyJhcHBfaWQiOjYyMDE0fQ"
         },
         "links": {
            "self": "https://api.unsplash.com/photos/xxWU76ALQE8",
            "html": "https://unsplash.com/photos/xxWU76ALQE8",
            "download": "https://unsplash.com/photos/xxWU76ALQE8/download",
            "download_location": "https://api.unsplash.com/photos/xxWU76ALQE8/download"
         },
         "user": "dan_carl5on",
         "tags": ["cloud", "clouds", "sunset"],
         "downloaded": false
      },
      {
         "id": "f8R_kFRACJ4",
         "description": "Driving in the mountains",
         "urls": {
            "raw": "https://images.unsplash.com/photo-1471673191832-eec29aa4b233?ixlib=rb-1.2.1&ixid=eyJhcHBfaWQiOjYyMDE0fQ",
            "full": "https://images.unsplash.com/photo-1471673191832-eec29aa4b233?ixlib=rb-1.2.1&q=85&fm=jpg&crop=entropy&cs=srgb&ixid=eyJhcHBfaWQiOjYyMDE0fQ",
            "regular": "https://images.unsplash.com/photo-1471673191832-eec29aa4b233?ixlib=rb-1.2.1&q=80&fm=jpg&crop=entropy&cs=tinysrgb&w=1080&fit=max&ixid=eyJhcHBfaWQiOjYyMDE0fQ",
            "small": "https://images.unsplash.com/photo-1471673191832-eec29aa4b233?ixlib=rb-1.2.1&q=80&fm=jpg&crop=entropy&cs=tinysrgb&w=400&fit=max&ixid=eyJhcHBfaWQiOjYyMDE0fQ",
            "thumb": "https://images.unsplash.com/photo-1471673191832-eec29aa4b233?ixlib=rb-1.2.1&q=80&fm=jpg&crop=entropy&cs=tinysrgb&w=200&fit=max&ixid=eyJhcHBfaWQiOjYyMDE0fQ"
         },
         "links": {
            "self": "https://api.unsplash.com/photos/f8R_kFRACJ4",
            "html": "https://unsplash.com/photos/f8R_kFRACJ4",
            "download": "https://unsplash.com/photos/f8R_kFRACJ4/download",
            "download_location": "https://api.unsplash.com/photos/f8R_kFRACJ4/download"
         },
         "user": "nathananderson",
         "tags": ["mountain", "cloud", "overcast"],
         "downloaded": false
      },
      {
         "id": "VLEyU1v7zn0",
         "description": "Watching the sunset",
         "urls": {
            "raw": "https://images.unsplash.com/photo-1471898554234-bcbfedd35134?ixlib=rb-1.2.1&ixid=eyJhcHBfaWQiOjYyMDE0fQ",
            "full": "https://images.unsplash.com/photo-1471898554234-bcbfedd35134?ixlib=rb-1.2.1&q=85&fm=jpg&crop=entropy&cs=srgb&ixid=eyJhcHBfaWQiOjYyMDE0fQ",
            "regular": "https://images.unsplash.com/photo-1471898554234-bcbfedd35134?ixlib=rb-1.2.1&q=80&fm=jpg&crop=entropy&cs=tinysrgb&w=1080&fit=max&ixid=eyJhcHBfaWQiOjYyMDE0fQ",
            "small": "https://images.unsplash.com/photo-1471898554234-bcbfedd35134?ixlib=rb-1.2.1&q=80&fm=jpg&crop=entropy&cs=tinysrgb&w=400&fit=max&ixid=eyJhcHBfaWQiOjYyMDE0fQ",
            "thumb": "https://images.unsplash.com/photo-1471898554234-bcbfedd35134?ixlib=rb-1.2.1&q=80&fm=jpg&crop=entropy&cs=tinysrgb&w=200&fit=max&ixid=eyJhcHBfaWQiOjYyMDE0fQ"
         },
         "links": {
            "self": "https://api.unsplash.com/photos/VLEyU1v7zn0",
            "html": "https://unsplash.com/photos/VLEyU1v7zn0",
            "download": "https://unsplash.com/photos/VLEyU1v7zn0/download",
            "download_location": "https://api.unsplash.com/photos/VLEyU1v7zn0/download"
         },
         "user": "jeremybishop",
         "tags": ["people", "hat", "clothing"],
         "downloaded": false
      },
      {
         "id": "f_bZb6scMDk",
         "description": null,
         "urls": {
            "raw": "https://images.unsplash.com/photo-1463331100952-5a05df40993c?ixlib=rb-1.2.1&ixid=eyJhcHBfaWQiOjYyMDE0fQ",
            "full": "https://images.unsplash.com/photo-1463331100952-5a05df40993c?ixlib=rb-1.2.1&q=85&fm=jpg&crop=entropy&cs=srgb&ixid=eyJhcHBfaWQiOjYyMDE0fQ",
            "regular": "https://images.unsplash.com/photo-1463331100952-5a05df40993c?ixlib=rb-1.2.1&q=80&fm=jpg&crop=entropy&cs=tinysrgb&w=1080&fit=max&ixid=eyJhcHBfaWQiOjYyMDE0fQ",
            "small": "https://images.unsplash.com/photo-1463331100952-5a05df40993c?ixlib=rb-1.2.1&q=80&fm=jpg&crop=entropy&cs=tinysrgb&w=400&fit=max&ixid=eyJhcHBfaWQiOjYyMDE0fQ",
            "thumb": "https://images.unsplash.com/photo-1463331100952-5a05df40993c?ixlib=rb-1.2.1&q=80&fm=jpg&crop=entropy&cs=tinysrgb&w=200&fit=max&ixid=eyJhcHBfaWQiOjYyMDE0fQ"
         },
         "links": {
            "self": "https://api.unsplash.com/photos/f_bZb6scMDk",
            "html": "https://unsplash.com/photos/f_bZb6scMDk",
            "download": "https://unsplash.com/photos/f_bZb6scMDk/download",
            "download_location": "https://api.unsplash.com/photos/f_bZb6scMDk/download"
         },
         "user": "ross_sokolovski",
         "tags": ["grey", "water", "wave"],
         "downloaded": false
      },
      {
         "id": "escJJ9mCfXY",
         "description": null,
         "urls": {
            "raw": "https://images.unsplash.com/photo-1438376902996-11719c362aef?ixlib=rb-1.2.1&ixid=eyJhcHBfaWQiOjYyMDE0fQ",
            "full": "https://images.unsplash.com/photo-1438376902996-11719c362aef?ixlib=rb-1.2.1&q=85&fm=jpg&crop=entropy&cs=srgb&ixid=eyJhcHBfaWQiOjYyMDE0fQ",
            "regular": "https://images.unsplash.com/photo-1438376902996-11719c362aef?ixlib=rb-1.2.1&q=80&fm=jpg&crop=entropy&cs=tinysrgb&w=1080&fit=max&ixid=eyJhcHBfaWQiOjYyMDE0fQ",
            "small": "https://images.unsplash.com/photo-1438376902996-11719c362aef?ixlib=rb-1.2.1&q=80&fm=jpg&crop=entropy&cs=tinysrgb&w=400&fit=max&ixid=eyJhcHBfaWQiOjYyMDE0fQ",
            "thumb": "https://images.unsplash.com/photo-1438376902996-11719c362aef?ixlib=rb-1.2.1&q=80&fm=jpg&crop=entropy&cs=tinysrgb&w=200&fit=max&ixid=eyJhcHBfaWQiOjYyMDE0fQ"
         },
         "links": {
            "self": "https://api.unsplash.com/photos/escJJ9mCfXY",
            "html": "https://unsplash.com/photos/escJJ9mCfXY",
            "download": "https://unsplash.com/photos/escJJ9mCfXY/download",
            "download_location": "https://api.unsplash.com/photos/escJJ9mCfXY/download"
         },
         "user": "ludwig_friborg",
         "tags": ["mountain", "nature", "clouds"],
         "downloaded": false
      },
      {
         "id": "tH5svvmwIvY",
         "description": "Winter mountains in New Mexico",
         "urls": {
            "raw": "https://images.unsplash.com/photo-1478095998943-7ab552a9061e?ixlib=rb-1.2.1&ixid=eyJhcHBfaWQiOjYyMDE0fQ",
            "full": "https://images.unsplash.com/photo-1478095998943-7ab552a9061e?ixlib=rb-1.2.1&q=85&fm=jpg&crop=entropy&cs=srgb&ixid=eyJhcHBfaWQiOjYyMDE0fQ",
            "regular": "https://images.unsplash.com/photo-1478095998943-7ab552a9061e?ixlib=rb-1.2.1&q=80&fm=jpg&crop=entropy&cs=tinysrgb&w=1080&fit=max&ixid=eyJhcHBfaWQiOjYyMDE0fQ",
            "small": "https://images.unsplash.com/photo-1478095998943-7ab552a9061e?ixlib=rb-1.2.1&q=80&fm=jpg&crop=entropy&cs=tinysrgb&w=400&fit=max&ixid=eyJhcHBfaWQiOjYyMDE0fQ",
            "thumb": "https://images.unsplash.com/photo-1478095998943-7ab552a9061e?ixlib=rb-1.2.1&q=80&fm=jpg&crop=entropy&cs=tinysrgb&w=200&fit=max&ixid=eyJhcHBfaWQiOjYyMDE0fQ"
         },
         "links": {
            "self": "https://api.unsplash.com/photos/tH5svvmwIvY",
            "html": "https://unsplash.com/photos/tH5svvmwIvY",
            "download": "https://unsplash.com/photos/tH5svvmwIvY/download",
            "download_location": "https://api.unsplash.com/photos/tH5svvmwIvY/download"
         },
         "user": "kieranleelewis",
         "tags": ["black-and-white", "new mexico", "snow"],
         "downloaded": false
      },
      {
         "id": "vpHCfunwDrQ",
         "description": null,
         "urls": {
            "raw": "https://images.unsplash.com/photo-1473654729523-203e25dfda10?ixlib=rb-1.2.1&ixid=eyJhcHBfaWQiOjYyMDE0fQ",
            "full": "https://images.unsplash.com/photo-1473654729523-203e25dfda10?ixlib=rb-1.2.1&q=85&fm=jpg&crop=entropy&cs=srgb&ixid=eyJhcHBfaWQiOjYyMDE0fQ",
            "regular": "https://images.unsplash.com/photo-1473654729523-203e25dfda10?ixlib=rb-1.2.1&q=80&fm=jpg&crop=entropy&cs=tinysrgb&w=1080&fit=max&ixid=eyJhcHBfaWQiOjYyMDE0fQ",
            "small": "https://images.unsplash.com/photo-1473654729523-203e25dfda10?ixlib=rb-1.2.1&q=80&fm=jpg&crop=entropy&cs=tinysrgb&w=400&fit=max&ixid=eyJhcHBfaWQiOjYyMDE0fQ",
            "thumb": "https://images.unsplash.com/photo-1473654729523-203e25dfda10?ixlib=rb-1.2.1&q=80&fm=jpg&crop=entropy&cs=tinysrgb&w=200&fit=max&ixid=eyJhcHBfaWQiOjYyMDE0fQ"
         },
         "links": {
            "self": "https://api.unsplash.com/photos/vpHCfunwDrQ",
            "html": "https://unsplash.com/photos/vpHCfunwDrQ",
            "download": "https://unsplash.com/photos/vpHCfunwDrQ/download",
            "download_location": "https://api.unsplash.com/photos/vpHCfunwDrQ/download"
         },
         "user": "efranciswork",
         "tags": ["nature", "iceland", "ice"],
         "downloaded": false
      },
      {
         "id": "eZN8cFYz2oY",
         "description": "Hang this photos on the wall. \r\nBuy prints https://society6.com/madbyte/prints",
         "urls": {
            "raw": "https://images.unsplash.com/photo-1427434869687-ab13f79ad4f1?ixlib=rb-1.2.1&ixid=eyJhcHBfaWQiOjYyMDE0fQ",
            "full": "https://images.unsplash.com/photo-1427434869687-ab13f79ad4f1?ixlib=rb-1.2.1&q=85&fm=jpg&crop=entropy&cs=srgb&ixid=eyJhcHBfaWQiOjYyMDE0fQ",
            "regular": "https://images.unsplash.com/photo-1427434869687-ab13f79ad4f1?ixlib=rb-1.2.1&q=80&fm=jpg&crop=entropy&cs=tinysrgb&w=1080&fit=max&ixid=eyJhcHBfaWQiOjYyMDE0fQ",
            "small": "https://images.unsplash.com/photo-1427434869687-ab13f79ad4f1?ixlib=rb-1.2.1&q=80&fm=jpg&crop=entropy&cs=tinysrgb&w=400&fit=max&ixid=eyJhcHBfaWQiOjYyMDE0fQ",
            "thumb": "https://images.unsplash.com/photo-1427434869687-ab13f79ad4f1?ixlib=rb-1.2.1&q=80&fm=jpg&crop=entropy&cs=tinysrgb&w=200&fit=max&ixid=eyJhcHBfaWQiOjYyMDE0fQ"
         },
         "links": {
            "self": "https://api.unsplash.com/photos/eZN8cFYz2oY",
            "html": "https://unsplash.com/photos/eZN8cFYz2oY",
            "download": "https://unsplash.com/photos/eZN8cFYz2oY/download",
            "download_location": "https://api.unsplash.com/photos/eZN8cFYz2oY/download"
         },
         "user": "madbyte",
         "tags": ["pier", "bridge", "mood"],
         "downloaded": false
      },
      {
         "id": "eqmzy8TcFYw",
         "description": null,
         "urls": {
            "raw": "https://images.unsplash.com/photo-1474247004289-efccca0b7f2a?ixlib=rb-1.2.1&ixid=eyJhcHBfaWQiOjYyMDE0fQ",
            "full": "https://images.unsplash.com/photo-1474247004289-efccca0b7f2a?ixlib=rb-1.2.1&q=85&fm=jpg&crop=entropy&cs=srgb&ixid=eyJhcHBfaWQiOjYyMDE0fQ",
            "regular": "https://images.unsplash.com/photo-1474247004289-efccca0b7f2a?ixlib=rb-1.2.1&q=80&fm=jpg&crop=entropy&cs=tinysrgb&w=1080&fit=max&ixid=eyJhcHBfaWQiOjYyMDE0fQ",
            "small": "https://images.unsplash.com/photo-1474247004289-efccca0b7f2a?ixlib=rb-1.2.1&q=80&fm=jpg&crop=entropy&cs=tinysrgb&w=400&fit=max&ixid=eyJhcHBfaWQiOjYyMDE0fQ",
            "thumb": "https://images.unsplash.com/photo-1474247004289-efccca0b7f2a?ixlib=rb-1.2.1&q=80&fm=jpg&crop=entropy&cs=tinysrgb&w=200&fit=max&ixid=eyJhcHBfaWQiOjYyMDE0fQ"
         },
         "links": {
            "self": "https://api.unsplash.com/photos/eqmzy8TcFYw",
            "html": "https://unsplash.com/photos/eqmzy8TcFYw",
            "download": "https://unsplash.com/photos/eqmzy8TcFYw/download",
            "download_location": "https://api.unsplash.com/photos/eqmzy8TcFYw/download"
         },
         "user": "araltasher",
         "tags": ["cloud", "sky", "weather"],
         "downloaded": false
      }
   ],
   "tags": [
      ["flora", "jar", "plant"],
      ["rain", "car", "highway"],
      ["grey", "black-and-white", "people"],
      ["dock", "pier", "water front"],
      ["highway", "road", "freeway"],
      ["forest", "tree", "moody"],
      ["grey", "people", "person"],
      ["forest", "moody", "mist"],
      ["mountain range", "peak", "mountain"],
      ["moody", "lighthouse", "coastal"],
      ["black-and-white", "dock", "pier"],
      ["road", "dirt road", "stone mountain state park"],
      ["mountain", "nature", "cloud"],
      ["grey", "ocean", "sea"],
      ["mist", "cloud", "bridge"],
      ["mountain", "nature", "clouds"],
      ["road", "clouds", "hills"],
      ["forest", "tree", "nature"],
      ["ocean", "sea", "coast"],
      ["ocean", "sea", "water"],
      ["city", "silhouette", "building"],
      ["cloud", "clouds", "sunset"],
      ["mountain", "cloud", "overcast"],
      ["people", "hat", "clothing"],
      ["grey", "water", "wave"],
      ["mountain", "nature", "clouds"],
      ["black-and-white", "new mexico", "snow"],
      ["nature", "iceland", "ice"],
      ["pier", "bridge", "mood"],
      ["cloud", "sky", "weather"]
   ],
   "keywords": "moody",
   "page": 2,
   "total_page": 146,
   "total_photo": 4368,
   "count": 30
}
